src/rtl/loproc_defines.vh
`timescale 1ns / 1ps
//////////////////////////////////////////////////////////////////////////////////
// Company:
// Engineer: Sanchith V M
//
// Create Date:    17:48:59 07/02/2022
// Design Name:
// Module Name:    loproc_defines
// Project Name: 	LoPROC v1.1
// Target Devices:
// Tool versions:
// Description:
//
// Dependencies:
//
// Revision:
// Revision 0.01 - File Created
// Additional Comments:
//
//////////////////////////////////////////////////////////////////////////////////
`define DATA_WIDTH            32
`define INSTRUCTION_WIDTH     32
`define REG_BANK_DEPTH        32
`define REG_BANK_ADDR_WIDTH   5
`define DATA_LOG2             5
`define POWER_MODES           4
`define POWER_MODES_LOG2      2

src/rtl/loproc_pc.v
`timescale 1ns / 1ps
//////////////////////////////////////////////////////////////////////////////////
// Company:
// Engineer: Sanchith V M
//
// Create Date:    18:01:15 07/30/2022
// Design Name:
// Module Name:    loproc_pc
// Project Name: LoPROC v1.1
// Target Devices:
// Tool versions:
// Description: This is the program counter that stores the address of the
//						next instruction to be processed
//
// Dependencies:
//
// Revision:
// Revision 0.01 - File Created
// Additional Comments:
//
//////////////////////////////////////////////////////////////////////////////////
`include "loproc_defines.vh"
module loproc_pc(

    input                                            clk,
    input                                            rst,

    input                                            load,
    input       [1:0]                                jump,
    input                                            interrupt,
    input       [`INSTRUCTION_WIDTH-1:0]             jmp_addr,
    input       [`INSTRUCTION_WIDTH-1:0]             interrupt_addr,

    output reg  [`INSTRUCTION_WIDTH-1:0]             next_instr_addr

    );

    localparam  JMP     = 2'h1;
    localparam  JMP_ADD = 2'h2;


    always @ (posedge clk or posedge rst) begin
        if (rst) begin
            next_instr_addr <= 32'h0;
        end else begin
            if(load) begin
                if(interrupt) begin
                    next_instr_addr <= interrupt_addr;
                end
                else if(jump==JMP) begin
                    next_instr_addr <= jmp_addr;
                end
                else if(jump==JMP_ADD) begin
                    next_instr_addr <= next_instr_addr + jmp_addr;
                end
                else begin
                    next_instr_addr <= next_instr_addr + 1'h1;
                end
            end
        end
    end

endmodule

src/tb/pc_tb.v
`include "loproc_defines.vh"

module pc_tb;
reg clk, rst;

reg load, interrupt;
reg [1:0] jump;

reg [`INSTRUCTION_WIDTH-1:0] jmp_addr;
reg [`INSTRUCTION_WIDTH-1:0] interrupt_addr;
wire [`INSTRUCTION_WIDTH-1:0] next_instr_addr;

loproc_pc dut (
	.clk(clk),
	.rst(rst),
	.load(load),
	.interrupt(interrupt),
	.jump(jump),
	.jmp_addr(jmp_addr),
	.interrupt_addr(interrupt_addr),
	.next_instr_addr(next_instr_addr)
);


initial begin
	$dumpfile("pc_dump.vcd");
	$dumpvars;
	clk <= 0; rst <= 0;
	load <= 0; interrupt <= 0;
	jump<= 0;

	jmp_addr <= 'h0; interrupt_addr <= 'h5000_2000;

	#5 rst <= 1;
	#10 rst <= 0;

	#10 load <= 1;

	#200 jump <= 'h1; jmp_addr <= 'h400;
	#10 jump <= 'h0; jmp_addr <= 'h0;

	#100 jump <= 'h2; jmp_addr <= 'h50;
	#10 jump <= 'h0;

	#50 load <= 0;

	#50 load <= 1;
	#20 interrupt <= 1;
	#10 interrupt <= 0;

	#50 $finish;
end

always #5 clk <= ~clk;

endmodule

sim/pc_tb/pc_dump.vcd
$date
	Sun May 19 17:48:11 2024
$end
$version
	Icarus Verilog
$end
$timescale
	1ps
$end
$scope module pc_tb $end
$var wire 32 ! next_instr_addr [31:0] $end
$var reg 1 " clk $end
$var reg 1 # interrupt $end
$var reg 32 $ interrupt_addr [31:0] $end
$var reg 32 % jmp_addr [31:0] $end
$var reg 2 & jump [1:0] $end
$var reg 1 ' load $end
$var reg 1 ( rst $end
$scope module dut $end
$var wire 1 " clk $end
$var wire 1 # interrupt $end
$var wire 32 ) interrupt_addr [31:0] $end
$var wire 32 * jmp_addr [31:0] $end
$var wire 2 + jump [1:0] $end
$var wire 1 ' load $end
$var wire 1 ( rst $end
$var reg 32 , next_instr_addr [31:0] $end
$upscope $end
$upscope $end
$enddefinitions $end
#0
$dumpvars
bx ,
b0 +
b0 *
b1010000000000000010000000000000 )
0(
0'
b0 &
b0 %
b1010000000000000010000000000000 $
0#
0"
bx !
$end
#5000
b0 !
b0 ,
1"
1(
#10000
0"
#15000
1"
0(
#20000
0"
#25000
b1 !
b1 ,
1"
1'
#30000
0"
#35000
b10 !
b10 ,
1"
#40000
0"
#45000
b11 !
b11 ,
1"
#50000
0"
#55000
b100 !
b100 ,
1"
#60000
0"
#65000
b101 !
b101 ,
1"
#70000
0"
#75000
b110 !
b110 ,
1"
#80000
0"
#85000
b111 !
b111 ,
1"
#90000
0"
#95000
b1000 !
b1000 ,
1"
#100000
0"
#105000
b1001 !
b1001 ,
1"
#110000
0"
#115000
b1010 !
b1010 ,
1"
#120000
0"
#125000
b1011 !
b1011 ,
1"
#130000
0"
#135000
b1100 !
b1100 ,
1"
#140000
0"
#145000
b1101 !
b1101 ,
1"
#150000
0"
#155000
b1110 !
b1110 ,
1"
#160000
0"
#165000
b1111 !
b1111 ,
1"
#170000
0"
#175000
b10000 !
b10000 ,
1"
#180000
0"
#185000
b10001 !
b10001 ,
1"
#190000
0"
#195000
b10010 !
b10010 ,
1"
#200000
0"
#205000
b10011 !
b10011 ,
1"
#210000
0"
#215000
b10100 !
b10100 ,
1"
#220000
0"
#225000
b10000000000 !
b10000000000 ,
1"
b10000000000 %
b10000000000 *
b1 &
b1 +
#230000
0"
#235000
b10000000001 !
b10000000001 ,
1"
b0 %
b0 *
b0 &
b0 +
#240000
0"
#245000
b10000000010 !
b10000000010 ,
1"
#250000
0"
#255000
b10000000011 !
b10000000011 ,
1"
#260000
0"
#265000
b10000000100 !
b10000000100 ,
1"
#270000
0"
#275000
b10000000101 !
b10000000101 ,
1"
#280000
0"
#285000
b10000000110 !
b10000000110 ,
1"
#290000
0"
#295000
b10000000111 !
b10000000111 ,
1"
#300000
0"
#305000
b10000001000 !
b10000001000 ,
1"
#310000
0"
#315000
b10000001001 !
b10000001001 ,
1"
#320000
0"
#325000
b10000001010 !
b10000001010 ,
1"
#330000
0"
#335000
b10001011010 !
b10001011010 ,
1"
b1010000 %
b1010000 *
b10 &
b10 +
#340000
0"
#345000
b10001011011 !
b10001011011 ,
1"
b0 &
b0 +
#350000
0"
#355000
b10001011100 !
b10001011100 ,
1"
#360000
0"
#365000
b10001011101 !
b10001011101 ,
1"
#370000
0"
#375000
b10001011110 !
b10001011110 ,
1"
#380000
0"
#385000
b10001011111 !
b10001011111 ,
1"
#390000
0"
#395000
1"
0'
#400000
0"
#405000
1"
#410000
0"
#415000
1"
#420000
0"
#425000
1"
#430000
0"
#435000
1"
#440000
0"
#445000
b10001100000 !
b10001100000 ,
1"
1'
#450000
0"
#455000
b10001100001 !
b10001100001 ,
1"
#460000
0"
#465000
b1010000000000000010000000000000 !
b1010000000000000010000000000000 ,
1"
1#
#470000
0"
#475000
b1010000000000000010000000000001 !
b1010000000000000010000000000001 ,
1"
0#
#480000
0"
#485000
b1010000000000000010000000000010 !
b1010000000000000010000000000010 ,
1"
#490000
0"
#495000
b1010000000000000010000000000011 !
b1010000000000000010000000000011 ,
1"
#500000
0"
#505000
b1010000000000000010000000000100 !
b1010000000000000010000000000100 ,
1"
#510000
0"
#515000
b1010000000000000010000000000101 !
b1010000000000000010000000000101 ,
1"
#520000
0"
#525000
b1010000000000000010000000000110 !
b1010000000000000010000000000110 ,
1"
