src/rtl/loproc_defines.vh
`timescale 1ns / 1ps
//////////////////////////////////////////////////////////////////////////////////
// Company:
// Engineer: Sanchith V M
//
// Create Date:    17:48:59 07/02/2022
// Design Name:
// Module Name:    loproc_defines
// Project Name: 	LoPROC v1.1
// Target Devices:
// Tool versions:
// Description:
//
// Dependencies:
//
// Revision:
// Revision 0.01 - File Created
// Additional Comments:
//
//////////////////////////////////////////////////////////////////////////////////
`define DATA_WIDTH            32
`define INSTRUCTION_WIDTH     32
`define REG_BANK_DEPTH        32
`define REG_BANK_ADDR_WIDTH   5
`define DATA_LOG2             5
`define POWER_MODES           4
`define POWER_MODES_LOG2      2

src/rtl/decoder_5_32.v
module decoder_5_32(in,y
    );
input[4:0] in;
output reg[31:0] y;
always@*
begin
casex(in)
5'b00000:y=32'h00000001;
5'b00001:y=32'h00000002;
5'b00010:y=32'h00000004;
5'b00011:y=32'h00000008;
5'b00100:y=32'h00000010;
5'b00101:y=32'h00000020;
5'b00110:y=32'h00000040;
5'b00111:y=32'h00000080;
5'b01000:y=32'h00000100;
5'b01001:y=32'h00000200;
5'b01010:y=32'h00000400;
5'b01011:y=32'h00000800;
5'b01100:y=32'h00001000;
5'b01101:y=32'h00002000;
5'b01110:y=32'h00004000;
5'b01111:y=32'h00008000;
5'b10000:y=32'h00010000;
5'b10001:y=32'h00020000;
5'b10010:y=32'h00040000;
5'b10011:y=32'h00080000;
5'b10100:y=32'h00100000;
5'b10101:y=32'h00200000;
5'b10110:y=32'h00400000;
5'b10111:y=32'h00800000;
5'b11000:y=32'h01000000;
5'b11001:y=32'h02000000;
5'b11010:y=32'h04000000;
5'b11011:y=32'h08000000;
5'b11100:y=32'h10000000;
5'b11101:y=32'h20000000;
5'b11110:y=32'h40000000;
5'b11111:y=32'h80000000;
default: y=32'h00000000;
endcase
end
endmodule

src/rtl/prencoder_32_5.v
module prencoder_32_5(in,y);
input[31:0] in;
output reg[4:0] y;

always@*
begin
casex(in)
32'b00000000000000000000000000000001:y=5'b00000;
32'b0000000000000000000000000000001x:y=5'b00001;
32'b000000000000000000000000000001xx:y=5'b00010;
32'b00000000000000000000000000001xxx:y=5'b00011;
32'b0000000000000000000000000001xxxx:y=5'b00100;
32'b000000000000000000000000001xxxxx:y=5'b00101;
32'b00000000000000000000000001xxxxxx:y=5'b00110;
32'b0000000000000000000000001xxxxxxx:y=5'b00111;
32'b000000000000000000000001xxxxxxxx:y=5'b01000;
32'b00000000000000000000001xxxxxxxxx:y=5'b01001;
32'b0000000000000000000001xxxxxxxxxx:y=5'b01010;
32'b000000000000000000001xxxxxxxxxxx:y=5'b01011;
32'b00000000000000000001xxxxxxxxxxxx:y=5'b01100;
32'b0000000000000000001xxxxxxxxxxxxx:y=5'b01101;
32'b000000000000000001xxxxxxxxxxxxxx:y=5'b01110;
32'b00000000000000001xxxxxxxxxxxxxxx:y=5'b01111;
32'b0000000000000001xxxxxxxxxxxxxxxx:y=5'b10000;
32'b000000000000001xxxxxxxxxxxxxxxxx:y=5'b10001;
32'b00000000000001xxxxxxxxxxxxxxxxxx:y=5'b10010;
32'b0000000000001xxxxxxxxxxxxxxxxxxx:y=5'b10011;
32'b000000000001xxxxxxxxxxxxxxxxxxxx:y=5'b10100;
32'b00000000001xxxxxxxxxxxxxxxxxxxxx:y=5'b10101;
32'b0000000001xxxxxxxxxxxxxxxxxxxxxx:y=5'b10110;
32'b000000001xxxxxxxxxxxxxxxxxxxxxxx:y=5'b10111;
32'b00000001xxxxxxxxxxxxxxxxxxxxxxxx:y=5'b11000;
32'b0000001xxxxxxxxxxxxxxxxxxxxxxxxx:y=5'b11001;
32'b000001xxxxxxxxxxxxxxxxxxxxxxxxxx:y=5'b11010;
32'b00001xxxxxxxxxxxxxxxxxxxxxxxxxxx:y=5'b11011;
32'b0001xxxxxxxxxxxxxxxxxxxxxxxxxxxx:y=5'b11100;
32'b001xxxxxxxxxxxxxxxxxxxxxxxxxxxxx:y=5'b11101;
32'b01xxxxxxxxxxxxxxxxxxxxxxxxxxxxxx:y=5'b11110;
32'b1xxxxxxxxxxxxxxxxxxxxxxxxxxxxxxx:y=5'b11111;
default:y=5'bzzzzz;
endcase
end
endmodule

src/rtl/loproc_multiplier.v
`timescale 1ns / 1ps
//////////////////////////////////////////////////////////////////////////////////
// Company:
// Engineer:
//
// Create Date:    19:03:17 07/16/2022
// Design Name:
// Module Name:    loproc_multiplier
// Project Name: 	LoPROC v1.1
// Target Devices:
// Tool versions:
// Description: This module is a multiplier based on an enhanced
//						version of add and shift algorithm
// Dependencies:
//
// Revision:
// Revision 0.01 - File Created
// Additional Comments:
//
//////////////////////////////////////////////////////////////////////////////////
`include "loproc_defines.vh"
//`include "prencoder_32_5.v"
//`include "decoder_5_32.v"
module loproc_multiplier(
		input 										mul_clk,
		input 										mul_rst,
		input 				[`DATA_WIDTH-1:0]				in1,
		input 				[`DATA_WIDTH-1:0]				in2,
		input 										valid_in,

		output 		 		[`DATA_WIDTH-1:0]				out_l,
		output 		 		[`DATA_WIDTH-1:0]				out_h,
		output reg 									valid_out
    );

	//Storing input data on valid
	reg 	[`DATA_WIDTH-1:0]	in1_reg, in2_reg;
	always @ (posedge mul_clk or posedge mul_rst) begin
		if (mul_rst) begin
			in1_reg <= 32'h0;
			in2_reg	<= 32'h0;
		end
		else if(valid_in)	begin
			in1_reg <= in1;
			in2_reg <= in2;
		end
	end

	//Enable for shifter and accumulator
	reg acc_enable;
	always@(posedge mul_clk or posedge mul_rst) begin
		if(mul_rst) begin
			acc_enable <= 1'b0;
		end
		else if(valid_in) begin
			acc_enable <= 1'b1;
		end
		else if(to_fb_sel_mux ==  'h0) begin
			acc_enable <= 1'b0;
		end
	end

	//Stage 1: Feedback loop
	//The feedback loop select mux
	wire [`DATA_WIDTH-1:0]	to_enc_register, to_fb_sel_mux;
	assign to_enc_register = valid_in? in2 : to_fb_sel_mux;

   	//reg for storing the value
	reg [`DATA_WIDTH-1:0]	enc_reg;
	always @ (posedge mul_clk or posedge mul_rst) begin
		if (mul_rst) begin
			enc_reg <= 32'h0;
		end else begin
			enc_reg <= to_enc_register;
		end
	end

	//Encoder and decoder
	wire [`DATA_LOG2-1:0] to_shifter;
	wire [`DATA_WIDTH-1:0] from_dec;

	prencoder_32_5 priority_encoder_inst(enc_reg, to_shifter);
	decoder_5_32 decoder_inst(to_shifter, from_dec);

	assign to_fb_sel_mux = enc_reg & ~from_dec;

	//Stage 2: Shifting
	wire [`DATA_WIDTH-1:0] shifter_out_l, shifter_out_h;
	assign {shifter_out_h, shifter_out_l} = acc_enable? (in1_reg<<to_shifter) : 'h0;

	//Stage 3: Accumulate
/*	
	reg [`DATA_WIDTH-1:0] shifter_out_l_reg, shifter_out_h_reg;
	reg l_carry, h_carry;
	always @ (posedge mul_clk or posedge mul_rst) begin
		if (mul_rst | ~acc_enable) begin
			shifter_out_l_reg <= 'b0;
			l_carry				<= 'b0;
		end else begin
			{l_carry, shifter_out_l_reg} <= shifter_out_l_reg + shifter_out_l;
		end
	end

	always @ (posedge mul_clk or posedge mul_rst) begin
		if (mul_rst | ~acc_enable) begin
			shifter_out_h_reg <= 'b0;
			h_carry						<= 'b0;
		end else begin
			{h_carry, shifter_out_h_reg} <= shifter_out_h_reg + shifter_out_h + l_carry;
		end
	end
*/
	//Valid out register
	always@(posedge mul_clk or posedge mul_rst) begin
		if(mul_rst | ~acc_enable) begin
			valid_out <= 1'b0;
		end
		else if(valid_out) begin
			valid_out <= 1'b0;
		end
		else if((to_fb_sel_mux=='h0) & acc_enable) begin
			valid_out <= 1'b1;
		end
	end
	
	reg [2*`DATA_WIDTH-1:0] shifter_acc;
	always@(posedge mul_clk or posedge mul_rst) begin
		if(mul_rst | ~acc_enable) begin
			shifter_acc <= 'h0;
		end
		else begin
			shifter_acc <= shifter_acc + {shifter_out_h,shifter_out_l};
		end
	end

	assign out_l = shifter_acc[`DATA_WIDTH-1:0];
	assign out_h = shifter_acc[2*`DATA_WIDTH-1:`DATA_WIDTH];

endmodule

src/tb/mult_tb.v
`include "loproc_defines.vh"
module mult_tb;
reg clk, rst, valid_in;
reg [`DATA_WIDTH-1:0] in1, in2;

wire [`DATA_WIDTH-1:0] out_l, out_h;
wire valid_out;

loproc_multiplier dut(
	.mul_clk (clk),
	.mul_rst (rst),

	.in1(in1),
	.in2(in2),
	.valid_in(valid_in),

	.out_l(out_l),
	.out_h(out_h),
	.valid_out(valid_out)
);

initial begin
	$dumpfile("mult_tb.vcd");
	$dumpvars;
	clk <= 0; rst <= 0;
	valid_in <= 0; in1 <= 'h0; in2 <= 'h0;
	#5 rst <= 1;
	#10 rst <= 0;	
	#10 in1 <= 'h4bba; in2 <= 'h100b;valid_in<= 1;
	#10 valid_in <= 0;


	#100 in1 <= 'hff00_bff1; in2 <= 'hff11_9956; valid_in <= 1;
	#10 valid_in <= 0;
	$display("done");
	#500 $finish;
end
always #5 clk <= ~clk;
endmodule

sim/mult_tb/mult_tb.vcd
$date
	Mon May 13 16:05:25 2024
$end
$version
	Icarus Verilog
$end
$timescale
	1ps
$end
$scope module mult_tb $end
$var wire 1 ! valid_out $end
$var wire 32 " out_l [31:0] $end
$var wire 32 # out_h [31:0] $end
$var reg 1 $ clk $end
$var reg 32 % in1 [31:0] $end
$var reg 32 & in2 [31:0] $end
$var reg 1 ' rst $end
$var reg 1 ( valid_in $end
$scope module dut $end
$var wire 32 ) in1 [31:0] $end
$var wire 32 * in2 [31:0] $end
$var wire 1 $ mul_clk $end
$var wire 1 ' mul_rst $end
$var wire 32 + to_fb_sel_mux [31:0] $end
$var wire 1 ( valid_in $end
$var wire 5 , to_shifter [4:0] $end
$var wire 32 - to_enc_register [31:0] $end
$var wire 32 . shifter_out_l [31:0] $end
$var wire 32 / shifter_out_h [31:0] $end
$var wire 32 0 out_l [31:0] $end
$var wire 32 1 out_h [31:0] $end
$var wire 32 2 from_dec [31:0] $end
$var reg 1 3 acc_enable $end
$var reg 32 4 enc_reg [31:0] $end
$var reg 32 5 in1_reg [31:0] $end
$var reg 32 6 in2_reg [31:0] $end
$var reg 64 7 shifter_acc [63:0] $end
$var reg 1 ! valid_out $end
$scope module decoder_inst $end
$var wire 5 8 in [4:0] $end
$var reg 32 9 y [31:0] $end
$upscope $end
$scope module priority_encoder_inst $end
$var wire 32 : in [31:0] $end
$var reg 5 ; y [4:0] $end
$upscope $end
$upscope $end
$upscope $end
$enddefinitions $end
#0
$dumpvars
bx ;
bx :
bx 9
bx 8
bx 7
bx 6
bx 5
bx 4
x3
bx 2
bx 1
bx 0
bx /
bx .
bx -
bx ,
bx +
b0 *
b0 )
0(
0'
b0 &
b0 %
0$
bx #
bx "
x!
$end
#5000
b0 .
b0 /
b1 2
b1 9
b0 -
bz ,
bz 8
bz ;
b0 +
b0 "
b0 0
b0 #
b0 1
b0 6
b0 5
03
b0 4
b0 :
0!
b0 7
1$
1'
#10000
0$
#15000
1$
0'
#20000
0$
#25000
b100101110111010000000000000 .
b1000000000000 2
b1000000000000 9
b1100 ,
b1100 8
b1100 ;
b1011 +
b1000000001011 6
b100101110111010 5
13
b1000000001011 4
b1000000001011 :
b1000000001011 -
1$
1(
b1000000001011 &
b1000000001011 *
b100101110111010 %
b100101110111010 )
#30000
0$
#35000
b11 +
b100101110111010000 .
b1000 2
b1000 9
b100101110111010000000000000 "
b100101110111010000000000000 0
b11 ,
b11 8
b11 ;
b100101110111010000000000000 7
b1011 4
b1011 :
b11 -
1$
0(
#40000
0$
#45000
b1 -
b1 +
b1001011101110100 .
b10 2
b10 9
b1 ,
b1 8
b1 ;
b100101111011111110111010000 "
b100101111011111110111010000 0
b11 4
b11 :
b100101111011111110111010000 7
1$
#50000
0$
#55000
b0 -
b0 +
b100101110111010 .
b1 2
b1 9
b100101111101001010101000100 "
b100101111101001010101000100 0
b0 ,
b0 8
b0 ;
b100101111101001010101000100 7
b1 4
b1 :
1$
#60000
0$
#65000
b0 .
bz ,
bz 8
bz ;
b100101111101110000011111110 "
b100101111101110000011111110 0
03
b0 4
b0 :
1!
b100101111101110000011111110 7
1$
#70000
0$
#75000
b0 "
b0 0
b0 7
0!
1$
#80000
0$
#85000
1$
#90000
0$
#95000
1$
#100000
0$
#105000
1$
#110000
0$
#115000
1$
#120000
0$
#125000
1$
#130000
0$
#135000
b10000000000000000000000000000000 2
b10000000000000000000000000000000 9
b10000000000000000000000000000000 .
b1111111100000000101111111111000 /
b11111 ,
b11111 8
b11111 ;
b1111111000100011001100101010110 +
b11111111000100011001100101010110 4
b11111111000100011001100101010110 :
13
b11111111000100011001100101010110 6
b11111111000000001011111111110001 5
b11111111000100011001100101010110 -
1$
1(
b11111111000100011001100101010110 &
b11111111000100011001100101010110 *
b11111111000000001011111111110001 %
b11111111000000001011111111110001 )
#140000
0$
#145000
b111111000100011001100101010110 +
b1000000000000000000000000000000 .
b111111110000000010111111111100 /
b1000000000000000000000000000000 2
b1000000000000000000000000000000 9
b11110 ,
b11110 8
b11110 ;
b10000000000000000000000000000000 "
b10000000000000000000000000000000 0
b1111111100000000101111111111000 #
b1111111100000000101111111111000 1
b1111111000100011001100101010110 4
b1111111000100011001100101010110 :
b111111110000000010111111111100010000000000000000000000000000000 7
b111111000100011001100101010110 -
1$
0(
#150000
0$
#155000
b11111000100011001100101010110 -
b11111000100011001100101010110 +
b100000000000000000000000000000 .
b11111111000000001011111111110 /
b100000000000000000000000000000 2
b100000000000000000000000000000 9
b11000000000000000000000000000000 "
b11000000000000000000000000000000 0
b10111111010000001000111111110100 #
b10111111010000001000111111110100 1
b11101 ,
b11101 8
b11101 ;
b1011111101000000100011111111010011000000000000000000000000000000 7
b111111000100011001100101010110 4
b111111000100011001100101010110 :
1$
#160000
0$
#165000
b1111000100011001100101010110 -
b1111000100011001100101010110 +
b10000000000000000000000000000 .
b1111111100000000101111111111 /
b10000000000000000000000000000 2
b10000000000000000000000000000 9
b11100 ,
b11100 8
b11100 ;
b11100000000000000000000000000000 "
b11100000000000000000000000000000 0
b11011111001000001010011111110010 #
b11011111001000001010011111110010 1
b11111000100011001100101010110 4
b11111000100011001100101010110 :
b1101111100100000101001111111001011100000000000000000000000000000 7
1$
#170000
0$
#175000
b111000100011001100101010110 -
b111000100011001100101010110 +
b10001000000000000000000000000000 .
b111111110000000010111111111 /
b1000000000000000000000000000 2
b1000000000000000000000000000 9
b11110000000000000000000000000000 "
b11110000000000000000000000000000 0
b11101111000100001011001111110001 #
b11101111000100001011001111110001 1
b11011 ,
b11011 8
b11011 ;
b1110111100010000101100111111000111110000000000000000000000000000 7
b1111000100011001100101010110 4
b1111000100011001100101010110 :
1$
#180000
0$
#185000
b11000100011001100101010110 -
b11000100011001100101010110 +
b11000100000000000000000000000000 .
b11111111000000001011111111 /
b100000000000000000000000000 2
b100000000000000000000000000 9
b11010 ,
b11010 8
b11010 ;
b1111000000000000000000000000000 "
b1111000000000000000000000000000 0
b11110111000010001011100111110001 #
b11110111000010001011100111110001 1
b111000100011001100101010110 4
b111000100011001100101010110 :
b1111011100001000101110011111000101111000000000000000000000000000 7
1$
#190000
0$
#195000
b1000100011001100101010110 -
b1000100011001100101010110 +
b11100010000000000000000000000000 .
b1111111100000000101111111 /
b10000000000000000000000000 2
b10000000000000000000000000 9
b111100000000000000000000000000 "
b111100000000000000000000000000 0
b11111011000001001011110011110001 #
b11111011000001001011110011110001 1
b11001 ,
b11001 8
b11001 ;
b1111101100000100101111001111000100111100000000000000000000000000 7
b11000100011001100101010110 4
b11000100011001100101010110 :
1$
#200000
0$
#205000
b100011001100101010110 -
b100011001100101010110 +
b11110001000000000000000000000000 .
b111111110000000010111111 /
b1000000000000000000000000 2
b1000000000000000000000000 9
b11000 ,
b11000 8
b11000 ;
b11110000000000000000000000000 "
b11110000000000000000000000000 0
b11111101000000101011111001110001 #
b11111101000000101011111001110001 1
b1000100011001100101010110 4
b1000100011001100101010110 :
b1111110100000010101111100111000100011110000000000000000000000000 7
1$
#210000
0$
#215000
b11001100101010110 -
b11001100101010110 +
b11111111000100000000000000000000 .
b11111111000000001011 /
b100000000000000000000 2
b100000000000000000000 9
b1111000000000000000000000000 "
b1111000000000000000000000000 0
b11111110000000011011111100110001 #
b11111110000000011011111100110001 1
b10100 ,
b10100 8
b10100 ;
b1111111000000001101111110011000100001111000000000000000000000000 7
b100011001100101010110 4
b100011001100101010110 :
1$
#220000
0$
#225000
b1001100101010110 -
b1001100101010110 +
b10111111111100010000000000000000 .
b1111111100000000 /
b10000000000000000 2
b10000000000000000 9
b10000 ,
b10000 8
b10000 ;
b1110000100000000000000000000 "
b1110000100000000000000000000 0
b11111110000100011010111100111101 #
b11111110000100011010111100111101 1
b11001100101010110 4
b11001100101010110 :
b1111111000010001101011110011110100001110000100000000000000000000 7
1$
#230000
0$
#235000
b1100101010110 -
b1100101010110 +
b1011111111110001000000000000000 .
b111111110000000 /
b1000000000000000 2
b1000000000000000 9
b11001110000000010000000000000000 "
b11001110000000010000000000000000 0
b11111110000100101010111000111101 #
b11111110000100101010111000111101 1
b1111 ,
b1111 8
b1111 ;
b1111111000010010101011100011110111001110000000010000000000000000 7
b1001100101010110 4
b1001100101010110 :
1$
#240000
0$
#245000
b100101010110 -
b100101010110 +
b1011111111110001000000000000 .
b111111110000 /
b1000000000000 2
b1000000000000 9
b1100 ,
b1100 8
b1100 ;
b101101111110011000000000000000 "
b101101111110011000000000000000 0
b11111110000100110010110110111110 #
b11111110000100110010110110111110 1
b1100101010110 4
b1100101010110 :
b1111111000010011001011011011111000101101111110011000000000000000 7
1$
#250000
0$
#255000
b101010110 -
b101010110 +
b101111111111000100000000000 .
b11111111000 /
b100000000000 2
b100000000000 9
b111001111110001001000000000000 "
b111001111110001001000000000000 0
b11111110000100110011110110101110 #
b11111110000100110011110110101110 1
b1011 ,
b1011 8
b1011 ;
b1111111000010011001111011010111000111001111110001001000000000000 7
b100101010110 4
b100101010110 :
1$
#260000
0$
#265000
b1010110 -
b1010110 +
b101111111111000100000000 .
b11111111 /
b100000000 2
b100000000 9
b1000 ,
b1000 8
b1000 ;
b111111111110000001100000000000 "
b111111111110000001100000000000 0
b11111110000100110100010110100110 #
b11111110000100110100010110100110 1
b101010110 4
b101010110 :
b1111111000010011010001011010011000111111111110000001100000000000 7
1$
#270000
0$
#275000
b10110 -
b10110 +
b11000000001011111111110001000000 .
b111111 /
b1000000 2
b1000000 9
b1000000101110000000100100000000 "
b1000000101110000000100100000000 0
b11111110000100110100011010100101 #
b11111110000100110100011010100101 1
b110 ,
b110 8
b110 ;
b1111111000010011010001101010010101000000101110000000100100000000 7
b1010110 4
b1010110 :
1$
#280000
0$
#285000
b110 -
b110 +
b11110000000010111111111100010000 .
b1111 /
b10000 2
b10000 9
b100 ,
b100 8
b100 ;
b111010000000010101000000 "
b111010000000010101000000 0
b11111110000100110100011011100101 #
b11111110000100110100011011100101 1
b10110 4
b10110 :
b1111111000010011010001101110010100000000111010000000010101000000 7
1$
#290000
0$
#295000
b10 -
b10 +
b11111100000000101111111111000100 .
b11 /
b100 2
b100 9
b11110000111101000000010001010000 "
b11110000111101000000010001010000 0
b11111110000100110100011011110100 #
b11111110000100110100011011110100 1
b10 ,
b10 8
b10 ;
b1111111000010011010001101111010011110000111101000000010001010000 7
b110 4
b110 :
1$
#300000
0$
#305000
b0 -
b0 +
b11111110000000010111111111100010 .
b1 /
b10 2
b10 9
b1 ,
b1 8
b1 ;
b11101100111101110000010000010100 "
b11101100111101110000010000010100 0
b11111110000100110100011011111000 #
b11111110000100110100011011111000 1
b10 4
b10 :
b1111111000010011010001101111100011101100111101110000010000010100 7
1$
#310000
0$
#315000
b1 2
b1 9
b0 .
b0 /
b11101010111110001000001111110110 "
b11101010111110001000001111110110 0
b11111110000100110100011011111010 #
b11111110000100110100011011111010 1
bz ,
bz 8
bz ;
b1111111000010011010001101111101011101010111110001000001111110110 7
1!
b0 4
b0 :
03
1$
#320000
0$
#325000
b0 "
b0 0
b0 #
b0 1
0!
b0 7
1$
